mousetracker/__init__.py
mousetracker/__pkginfo__.py
mousetracker/gui/__init__.py
mousetracker/gui/dialogs/__init__.py
mousetracker/gui/dialogs/group_contents_dialog.py
mousetracker/gui/dialogs/plot_dialog.py
mousetracker/gui/main_windows/__init__.py
mousetracker/gui/main_windows/main_window.py
mousetracker/gui/views/__init__.py
mousetracker/gui/views/copy_pastable_tableview.py
mousetracker/gui/views/droppable_listview.py
mousetracker/gui/views/groups_listview.py
mousetracker/gui/widgets/__init__.py
mousetracker/gui/widgets/checkable_combobox.py
mousetracker/gui/widgets/groups_widget.py
mousetracker/gui/widgets/logger_widget.py
mousetracker/gui/widgets/statistics_widget.py
mousetracker/icons/mousetracker.png
mousetracker/kernel/__init__.py
mousetracker/kernel/models/__init__.py
mousetracker/kernel/models/available_samples_model.py
mousetracker/kernel/models/droppable_model.py
mousetracker/kernel/models/excel_files_model.py
mousetracker/kernel/models/groups_model.py
mousetracker/kernel/models/mouse_monitoring_model.py
mousetracker/kernel/models/pandas_data_model.py
mousetracker/kernel/models/pvalues_data_model.py
mousetracker/kernel/utils/__init__.py
mousetracker/kernel/utils/progress_bar.py
mousetracker-0.0.10.data/scripts/mousetracker
mousetracker-0.0.10.dist-info/LICENSE
mousetracker-0.0.10.dist-info/METADATA
mousetracker-0.0.10.dist-info/WHEEL
mousetracker-0.0.10.dist-info/top_level.txt
mousetracker-0.0.10.dist-info/RECORD
